{"file:///c%3A/Users/zj/Desktop/%E7%BC%96%E8%AF%91%E5%AE%9E%E9%AA%8C/Compiler/src/lexical/CategoryCode.java":{"language":"Java","code":42,"comment":0,"blank":2},"file:///c%3A/Users/zj/Desktop/%E7%BC%96%E8%AF%91%E5%AE%9E%E9%AA%8C/Compiler/.idea/modules.xml":{"language":"XML","code":8,"comment":0,"blank":0},"file:///c%3A/Users/zj/Desktop/%E7%BC%96%E8%AF%91%E5%AE%9E%E9%AA%8C/Compiler/Compiler.iml":{"language":"XML","code":11,"comment":0,"blank":0},"file:///c%3A/Users/zj/Desktop/%E7%BC%96%E8%AF%91%E5%AE%9E%E9%AA%8C/Compiler/.idea/misc.xml":{"language":"XML","code":6,"comment":0,"blank":0},"file:///c%3A/Users/zj/Desktop/%E7%BC%96%E8%AF%91%E5%AE%9E%E9%AA%8C/Compiler/src/syntaxAnalyser/TreeNode.java":{"language":"Java","code":3,"comment":0,"blank":3},"file:///c%3A/Users/zj/Desktop/%E7%BC%96%E8%AF%91%E5%AE%9E%E9%AA%8C/Compiler/src/lexical/LexicalManager.java":{"language":"Java","code":55,"comment":13,"blank":12},"file:///c%3A/Users/zj/Desktop/%E7%BC%96%E8%AF%91%E5%AE%9E%E9%AA%8C/Compiler/src/error/ErrorHandler.java":{"language":"Java","code":6,"comment":0,"blank":2},"file:///c%3A/Users/zj/Desktop/%E7%BC%96%E8%AF%91%E5%AE%9E%E9%AA%8C/Compiler/src/lexical/LexicalAnalyser.java":{"language":"Java","code":205,"comment":6,"blank":11},"file:///c%3A/Users/zj/Desktop/%E7%BC%96%E8%AF%91%E5%AE%9E%E9%AA%8C/Compiler/src/lexical/Symbol.java":{"language":"Java","code":8,"comment":0,"blank":3},"file:///c%3A/Users/zj/Desktop/%E7%BC%96%E8%AF%91%E5%AE%9E%E9%AA%8C/Compiler/README.md":{"language":"Markdown","code":10,"comment":0,"blank":9},"file:///c%3A/Users/zj/Desktop/%E7%BC%96%E8%AF%91%E5%AE%9E%E9%AA%8C/Compiler/src/lexical/Reader.java":{"language":"Java","code":40,"comment":0,"blank":7},"file:///c%3A/Users/zj/Desktop/%E7%BC%96%E8%AF%91%E5%AE%9E%E9%AA%8C/Compiler/src/error/ParsingFailedException.java":{"language":"Java","code":3,"comment":0,"blank":3},"file:///c%3A/Users/zj/Desktop/%E7%BC%96%E8%AF%91%E5%AE%9E%E9%AA%8C/Compiler/src/Compiler.java":{"language":"Java","code":16,"comment":1,"blank":3},"file:///c%3A/Users/zj/Desktop/%E7%BC%96%E8%AF%91%E5%AE%9E%E9%AA%8C/Compiler/src/syntaxAnalyser/nodes/Cond.java":{"language":"Java","code":17,"comment":1,"blank":6},"file:///c%3A/Users/zj/Desktop/%E7%BC%96%E8%AF%91%E5%AE%9E%E9%AA%8C/Compiler/.idea/uiDesigner.xml":{"language":"XML","code":124,"comment":0,"blank":0},"file:///c%3A/Users/zj/Desktop/%E7%BC%96%E8%AF%91%E5%AE%9E%E9%AA%8C/Compiler/.idea/checkstyle-idea.xml":{"language":"XML","code":16,"comment":0,"blank":0},"file:///c%3A/Users/zj/Desktop/%E7%BC%96%E8%AF%91%E5%AE%9E%E9%AA%8C/Compiler/src/syntaxAnalyser/nodes/ConstExp.java":{"language":"Java","code":18,"comment":0,"blank":6},"file:///c%3A/Users/zj/Desktop/%E7%BC%96%E8%AF%91%E5%AE%9E%E9%AA%8C/Compiler/src/syntaxAnalyser/nodes/ConstDef.java":{"language":"Java","code":33,"comment":1,"blank":8},"file:///c%3A/Users/zj/Desktop/%E7%BC%96%E8%AF%91%E5%AE%9E%E9%AA%8C/Compiler/src/syntaxAnalyser/nodes/ConstDecl.java":{"language":"Java","code":34,"comment":1,"blank":7},"file:///c%3A/Users/zj/Desktop/%E7%BC%96%E8%AF%91%E5%AE%9E%E9%AA%8C/Compiler/src/syntaxAnalyser/nodes/Block.java":{"language":"Java","code":29,"comment":1,"blank":8},"file:///c%3A/Users/zj/Desktop/%E7%BC%96%E8%AF%91%E5%AE%9E%E9%AA%8C/Compiler/src/syntaxAnalyser/nodes/BlockItem.java":{"language":"Java","code":27,"comment":1,"blank":9},"file:///c%3A/Users/zj/Desktop/%E7%BC%96%E8%AF%91%E5%AE%9E%E9%AA%8C/Compiler/src/syntaxAnalyser/nodes/BType.java":{"language":"Java","code":21,"comment":0,"blank":6},"file:///c%3A/Users/zj/Desktop/%E7%BC%96%E8%AF%91%E5%AE%9E%E9%AA%8C/Compiler/src/syntaxAnalyser/nodes/AddExp.java":{"language":"Java","code":18,"comment":0,"blank":6},"file:///c%3A/Users/zj/Desktop/%E7%BC%96%E8%AF%91%E5%AE%9E%E9%AA%8C/Compiler/src/syntaxAnalyser/nodes/Exp.java":{"language":"Java","code":18,"comment":1,"blank":6},"file:///c%3A/Users/zj/Desktop/%E7%BC%96%E8%AF%91%E5%AE%9E%E9%AA%8C/Compiler/src/syntaxAnalyser/nodes/CompUnit.java":{"language":"Java","code":39,"comment":0,"blank":7},"file:///c%3A/Users/zj/Desktop/%E7%BC%96%E8%AF%91%E5%AE%9E%E9%AA%8C/Compiler/src/syntaxAnalyser/nodes/ConstInitVal.java":{"language":"Java","code":39,"comment":2,"blank":11},"file:///c%3A/Users/zj/Desktop/%E7%BC%96%E8%AF%91%E5%AE%9E%E9%AA%8C/Compiler/src/syntaxAnalyser/nodes/Decl.java":{"language":"Java","code":30,"comment":1,"blank":8},"file:///c%3A/Users/zj/Desktop/%E7%BC%96%E8%AF%91%E5%AE%9E%E9%AA%8C/Compiler/src/syntaxAnalyser/nodes/EqExp.java":{"language":"Java","code":18,"comment":0,"blank":6},"file:///c%3A/Users/zj/Desktop/%E7%BC%96%E8%AF%91%E5%AE%9E%E9%AA%8C/Compiler/out/production/Compiler/ErrorHandler.class":{"language":"Java","code":8,"comment":0,"blank":0},"file:///c%3A/Users/zj/Desktop/%E7%BC%96%E8%AF%91%E5%AE%9E%E9%AA%8C/Compiler/out/production/Compiler/LexicalAnalyser.class":{"language":"Java","code":81,"comment":0,"blank":0},"file:///c%3A/Users/zj/Desktop/%E7%BC%96%E8%AF%91%E5%AE%9E%E9%AA%8C/Compiler/src/syntaxAnalyser/nodes/FuncRParams.java":{"language":"Java","code":29,"comment":1,"blank":7},"file:///c%3A/Users/zj/Desktop/%E7%BC%96%E8%AF%91%E5%AE%9E%E9%AA%8C/Compiler/out/production/Compiler/Symbol.class":{"language":"Java","code":14,"comment":0,"blank":0},"file:///c%3A/Users/zj/Desktop/%E7%BC%96%E8%AF%91%E5%AE%9E%E9%AA%8C/Compiler/out/production/Compiler/Reader.class":{"language":"Java","code":26,"comment":0,"blank":0},"file:///c%3A/Users/zj/Desktop/%E7%BC%96%E8%AF%91%E5%AE%9E%E9%AA%8C/Compiler/src/syntaxAnalyser/nodes/FuncType.java":{"language":"Java","code":25,"comment":1,"blank":9},"file:///c%3A/Users/zj/Desktop/%E7%BC%96%E8%AF%91%E5%AE%9E%E9%AA%8C/Compiler/out/production/Compiler/Compiler.class":{"language":"Java","code":26,"comment":0,"blank":0},"file:///c%3A/Users/zj/Desktop/%E7%BC%96%E8%AF%91%E5%AE%9E%E9%AA%8C/Compiler/src/syntaxAnalyser/nodes/FuncDef.java":{"language":"Java","code":32,"comment":1,"blank":8},"file:///c%3A/Users/zj/Desktop/%E7%BC%96%E8%AF%91%E5%AE%9E%E9%AA%8C/Compiler/src/syntaxAnalyser/nodes/FuncFParam.java":{"language":"Java","code":35,"comment":1,"blank":7},"file:///c%3A/Users/zj/Desktop/%E7%BC%96%E8%AF%91%E5%AE%9E%E9%AA%8C/Compiler/src/syntaxAnalyser/nodes/ForStmt.java":{"language":"Java","code":27,"comment":1,"blank":7},"file:///c%3A/Users/zj/Desktop/%E7%BC%96%E8%AF%91%E5%AE%9E%E9%AA%8C/Compiler/src/syntaxAnalyser/nodes/InitVal.java":{"language":"Java","code":42,"comment":2,"blank":10},"file:///c%3A/Users/zj/Desktop/%E7%BC%96%E8%AF%91%E5%AE%9E%E9%AA%8C/Compiler/src/syntaxAnalyser/nodes/FuncFParams.java":{"language":"Java","code":30,"comment":1,"blank":8},"file:///c%3A/Users/zj/Desktop/%E7%BC%96%E8%AF%91%E5%AE%9E%E9%AA%8C/Compiler/bin/lexical/LexicalManager.class":{"language":"Java","code":24,"comment":4,"blank":0},"file:///c%3A/Users/zj/Desktop/%E7%BC%96%E8%AF%91%E5%AE%9E%E9%AA%8C/Compiler/out/production/Compiler/CategoryCode.class":{"language":"Java","code":24,"comment":0,"blank":0},"file:///c%3A/Users/zj/Desktop/%E7%BC%96%E8%AF%91%E5%AE%9E%E9%AA%8C/Compiler/bin/syntaxAnalyser/TreeNode.class":{"language":"Java","code":3,"comment":0,"blank":0},"file:///c%3A/Users/zj/Desktop/%E7%BC%96%E8%AF%91%E5%AE%9E%E9%AA%8C/Compiler/bin/lexical/Symbol.class":{"language":"Java","code":15,"comment":0,"blank":0},"file:///c%3A/Users/zj/Desktop/%E7%BC%96%E8%AF%91%E5%AE%9E%E9%AA%8C/Compiler/bin/lexical/Reader.class":{"language":"Java","code":20,"comment":0,"blank":0},"file:///c%3A/Users/zj/Desktop/%E7%BC%96%E8%AF%91%E5%AE%9E%E9%AA%8C/Compiler/bin/lexical/LexicalAnalyser.class":{"language":"Java","code":47,"comment":0,"blank":0},"file:///c%3A/Users/zj/Desktop/%E7%BC%96%E8%AF%91%E5%AE%9E%E9%AA%8C/Compiler/bin/lexical/CategoryCode.class":{"language":"Java","code":21,"comment":0,"blank":0},"file:///c%3A/Users/zj/Desktop/%E7%BC%96%E8%AF%91%E5%AE%9E%E9%AA%8C/Compiler/bin/syntaxAnalyser/nodes/VarDef.class":{"language":"Java","code":25,"comment":0,"blank":0},"file:///c%3A/Users/zj/Desktop/%E7%BC%96%E8%AF%91%E5%AE%9E%E9%AA%8C/Compiler/bin/syntaxAnalyser/nodes/VarDecl.class":{"language":"Java","code":26,"comment":0,"blank":0},"file:///c%3A/Users/zj/Desktop/%E7%BC%96%E8%AF%91%E5%AE%9E%E9%AA%8C/Compiler/bin/syntaxAnalyser/nodes/UnaryExp.class":{"language":"Java","code":16,"comment":0,"blank":0},"file:///c%3A/Users/zj/Desktop/%E7%BC%96%E8%AF%91%E5%AE%9E%E9%AA%8C/Compiler/bin/syntaxAnalyser/nodes/RelExp.class":{"language":"Java","code":15,"comment":0,"blank":0},"file:///c%3A/Users/zj/Desktop/%E7%BC%96%E8%AF%91%E5%AE%9E%E9%AA%8C/Compiler/bin/syntaxAnalyser/nodes/Stmt.class":{"language":"Java","code":15,"comment":0,"blank":0},"file:///c%3A/Users/zj/Desktop/%E7%BC%96%E8%AF%91%E5%AE%9E%E9%AA%8C/Compiler/bin/syntaxAnalyser/nodes/UnaryOp.class":{"language":"Java","code":15,"comment":0,"blank":0},"file:///c%3A/Users/zj/Desktop/%E7%BC%96%E8%AF%91%E5%AE%9E%E9%AA%8C/Compiler/bin/syntaxAnalyser/nodes/Number.class":{"language":"Java","code":15,"comment":0,"blank":0},"file:///c%3A/Users/zj/Desktop/%E7%BC%96%E8%AF%91%E5%AE%9E%E9%AA%8C/Compiler/bin/syntaxAnalyser/nodes/MulExp.class":{"language":"Java","code":15,"comment":0,"blank":0},"file:///c%3A/Users/zj/Desktop/%E7%BC%96%E8%AF%91%E5%AE%9E%E9%AA%8C/Compiler/bin/syntaxAnalyser/nodes/PrimaryExp.class":{"language":"Java","code":7,"comment":0,"blank":0},"file:///c%3A/Users/zj/Desktop/%E7%BC%96%E8%AF%91%E5%AE%9E%E9%AA%8C/Compiler/bin/error/ErrorHandler.class":{"language":"Java","code":9,"comment":0,"blank":0},"file:///c%3A/Users/zj/Desktop/%E7%BC%96%E8%AF%91%E5%AE%9E%E9%AA%8C/Compiler/bin/syntaxAnalyser/nodes/InitVal.class":{"language":"Java","code":25,"comment":0,"blank":0},"file:///c%3A/Users/zj/Desktop/%E7%BC%96%E8%AF%91%E5%AE%9E%E9%AA%8C/Compiler/bin/syntaxAnalyser/nodes/MainFuncDef.class":{"language":"Java","code":21,"comment":0,"blank":0},"file:///c%3A/Users/zj/Desktop/%E7%BC%96%E8%AF%91%E5%AE%9E%E9%AA%8C/Compiler/bin/syntaxAnalyser/nodes/FuncType.class":{"language":"Java","code":20,"comment":0,"blank":0},"file:///c%3A/Users/zj/Desktop/%E7%BC%96%E8%AF%91%E5%AE%9E%E9%AA%8C/Compiler/bin/syntaxAnalyser/nodes/FuncFParams.class":{"language":"Java","code":24,"comment":0,"blank":0},"file:///c%3A/Users/zj/Desktop/%E7%BC%96%E8%AF%91%E5%AE%9E%E9%AA%8C/Compiler/bin/syntaxAnalyser/nodes/LOrExp.class":{"language":"Java","code":15,"comment":0,"blank":0},"file:///c%3A/Users/zj/Desktop/%E7%BC%96%E8%AF%91%E5%AE%9E%E9%AA%8C/Compiler/bin/syntaxAnalyser/nodes/LVal.class":{"language":"Java","code":15,"comment":0,"blank":0},"file:///c%3A/Users/zj/Desktop/%E7%BC%96%E8%AF%91%E5%AE%9E%E9%AA%8C/Compiler/bin/syntaxAnalyser/nodes/FuncFParam.class":{"language":"Java","code":25,"comment":0,"blank":0},"file:///c%3A/Users/zj/Desktop/%E7%BC%96%E8%AF%91%E5%AE%9E%E9%AA%8C/Compiler/bin/syntaxAnalyser/nodes/FuncDef.class":{"language":"Java","code":23,"comment":0,"blank":0},"file:///c%3A/Users/zj/Desktop/%E7%BC%96%E8%AF%91%E5%AE%9E%E9%AA%8C/Compiler/bin/syntaxAnalyser/nodes/Exp.class":{"language":"Java","code":15,"comment":0,"blank":0},"file:///c%3A/Users/zj/Desktop/%E7%BC%96%E8%AF%91%E5%AE%9E%E9%AA%8C/Compiler/bin/syntaxAnalyser/nodes/LAndExp.class":{"language":"Java","code":15,"comment":0,"blank":0},"file:///c%3A/Users/zj/Desktop/%E7%BC%96%E8%AF%91%E5%AE%9E%E9%AA%8C/Compiler/bin/syntaxAnalyser/nodes/Decl.class":{"language":"Java","code":22,"comment":0,"blank":0},"file:///c%3A/Users/zj/Desktop/%E7%BC%96%E8%AF%91%E5%AE%9E%E9%AA%8C/Compiler/bin/syntaxAnalyser/nodes/ConstExp.class":{"language":"Java","code":16,"comment":0,"blank":0},"file:///c%3A/Users/zj/Desktop/%E7%BC%96%E8%AF%91%E5%AE%9E%E9%AA%8C/Compiler/bin/syntaxAnalyser/nodes/ForStmt.class":{"language":"Java","code":15,"comment":0,"blank":0},"file:///c%3A/Users/zj/Desktop/%E7%BC%96%E8%AF%91%E5%AE%9E%E9%AA%8C/Compiler/bin/syntaxAnalyser/nodes/ConstInitVal.class":{"language":"Java","code":25,"comment":0,"blank":0},"file:///c%3A/Users/zj/Desktop/%E7%BC%96%E8%AF%91%E5%AE%9E%E9%AA%8C/Compiler/bin/syntaxAnalyser/nodes/FuncRParams.class":{"language":"Java","code":15,"comment":0,"blank":0},"file:///c%3A/Users/zj/Desktop/%E7%BC%96%E8%AF%91%E5%AE%9E%E9%AA%8C/Compiler/bin/syntaxAnalyser/nodes/EqExp.class":{"language":"Java","code":16,"comment":0,"blank":0},"file:///c%3A/Users/zj/Desktop/%E7%BC%96%E8%AF%91%E5%AE%9E%E9%AA%8C/Compiler/bin/syntaxAnalyser/nodes/ConstDecl.class":{"language":"Java","code":26,"comment":0,"blank":0},"file:///c%3A/Users/zj/Desktop/%E7%BC%96%E8%AF%91%E5%AE%9E%E9%AA%8C/Compiler/bin/syntaxAnalyser/nodes/BType.class":{"language":"Java","code":20,"comment":0,"blank":0},"file:///c%3A/Users/zj/Desktop/%E7%BC%96%E8%AF%91%E5%AE%9E%E9%AA%8C/Compiler/bin/syntaxAnalyser/nodes/Block.class":{"language":"Java","code":16,"comment":0,"blank":0},"file:///c%3A/Users/zj/Desktop/%E7%BC%96%E8%AF%91%E5%AE%9E%E9%AA%8C/Compiler/bin/syntaxAnalyser/nodes/ConstDef.class":{"language":"Java","code":27,"comment":0,"blank":0},"file:///c%3A/Users/zj/Desktop/%E7%BC%96%E8%AF%91%E5%AE%9E%E9%AA%8C/Compiler/src/syntaxAnalyser/nodes/UnaryOp.java":{"language":"Java","code":24,"comment":1,"blank":6},"file:///c%3A/Users/zj/Desktop/%E7%BC%96%E8%AF%91%E5%AE%9E%E9%AA%8C/Compiler/bin/syntaxAnalyser/nodes/Cond.class":{"language":"Java","code":15,"comment":0,"blank":0},"file:///c%3A/Users/zj/Desktop/%E7%BC%96%E8%AF%91%E5%AE%9E%E9%AA%8C/Compiler/src/syntaxAnalyser/nodes/UnaryExp.java":{"language":"Java","code":41,"comment":4,"blank":7},"file:///c%3A/Users/zj/Desktop/%E7%BC%96%E8%AF%91%E5%AE%9E%E9%AA%8C/Compiler/src/syntaxAnalyser/nodes/VarDef.java":{"language":"Java","code":34,"comment":1,"blank":8},"file:///c%3A/Users/zj/Desktop/%E7%BC%96%E8%AF%91%E5%AE%9E%E9%AA%8C/Compiler/src/syntaxAnalyser/nodes/VarDecl.java":{"language":"Java","code":32,"comment":1,"blank":8},"file:///c%3A/Users/zj/Desktop/%E7%BC%96%E8%AF%91%E5%AE%9E%E9%AA%8C/Compiler/bin/syntaxAnalyser/nodes/CompUnit.class":{"language":"Java","code":25,"comment":0,"blank":0},"file:///c%3A/Users/zj/Desktop/%E7%BC%96%E8%AF%91%E5%AE%9E%E9%AA%8C/Compiler/src/syntaxAnalyser/nodes/PrimaryExp.java":{"language":"Java","code":38,"comment":1,"blank":7},"file:///c%3A/Users/zj/Desktop/%E7%BC%96%E8%AF%91%E5%AE%9E%E9%AA%8C/Compiler/bin/syntaxAnalyser/nodes/BlockItem.class":{"language":"Java","code":15,"comment":0,"blank":0},"file:///c%3A/Users/zj/Desktop/%E7%BC%96%E8%AF%91%E5%AE%9E%E9%AA%8C/Compiler/bin/error/ParsingFailedException.class":{"language":"Java","code":5,"comment":0,"blank":0},"file:///c%3A/Users/zj/Desktop/%E7%BC%96%E8%AF%91%E5%AE%9E%E9%AA%8C/Compiler/src/syntaxAnalyser/nodes/Stmt.java":{"language":"Java","code":110,"comment":22,"blank":10},"file:///c%3A/Users/zj/Desktop/%E7%BC%96%E8%AF%91%E5%AE%9E%E9%AA%8C/Compiler/src/syntaxAnalyser/nodes/MulExp.java":{"language":"Java","code":18,"comment":1,"blank":6},"file:///c%3A/Users/zj/Desktop/%E7%BC%96%E8%AF%91%E5%AE%9E%E9%AA%8C/Compiler/src/syntaxAnalyser/nodes/RelExp.java":{"language":"Java","code":18,"comment":0,"blank":6},"file:///c%3A/Users/zj/Desktop/%E7%BC%96%E8%AF%91%E5%AE%9E%E9%AA%8C/Compiler/bin/syntaxAnalyser/nodes/AddExp.class":{"language":"Java","code":15,"comment":0,"blank":0},"file:///c%3A/Users/zj/Desktop/%E7%BC%96%E8%AF%91%E5%AE%9E%E9%AA%8C/Compiler/src/syntaxAnalyser/nodes/Number.java":{"language":"Java","code":18,"comment":0,"blank":6},"file:///c%3A/Users/zj/Desktop/%E7%BC%96%E8%AF%91%E5%AE%9E%E9%AA%8C/Compiler/src/syntaxAnalyser/nodes/LVal.java":{"language":"Java","code":30,"comment":1,"blank":8},"file:///c%3A/Users/zj/Desktop/%E7%BC%96%E8%AF%91%E5%AE%9E%E9%AA%8C/Compiler/src/syntaxAnalyser/nodes/MainFuncDef.java":{"language":"Java","code":30,"comment":1,"blank":8},"file:///c%3A/Users/zj/Desktop/%E7%BC%96%E8%AF%91%E5%AE%9E%E9%AA%8C/Compiler/bin/Compiler.class":{"language":"Java","code":27,"comment":0,"blank":0},"file:///c%3A/Users/zj/Desktop/%E7%BC%96%E8%AF%91%E5%AE%9E%E9%AA%8C/Compiler/src/syntaxAnalyser/nodes/LOrExp.java":{"language":"Java","code":18,"comment":0,"blank":6},"file:///c%3A/Users/zj/Desktop/%E7%BC%96%E8%AF%91%E5%AE%9E%E9%AA%8C/Compiler/src/syntaxAnalyser/nodes/LAndExp.java":{"language":"Java","code":18,"comment":0,"blank":6}}